pysd/__init__.py
pysd/__main__.py
pysd/_version.py
pysd/pysd.py
pysd/builders/__init__.py
pysd/builders/python/__init__.py
pysd/builders/python/imports.py
pysd/builders/python/namespace.py
pysd/builders/python/python_expressions_builder.py
pysd/builders/python/python_functions.py
pysd/builders/python/python_model_builder.py
pysd/builders/python/subscripts.py
pysd/cli/__init__.py
pysd/cli/main.py
pysd/cli/parser.py
pysd/py_backend/__init__.py
pysd/py_backend/allocation.py
pysd/py_backend/cache.py
pysd/py_backend/components.py
pysd/py_backend/data.py
pysd/py_backend/external.py
pysd/py_backend/functions.py
pysd/py_backend/lookups.py
pysd/py_backend/model.py
pysd/py_backend/output.py
pysd/py_backend/statefuls.py
pysd/py_backend/utils.py
pysd/tools/__init__.py
pysd/tools/benchmarking.py
pysd/tools/ncfiles.py
pysd/translators/__init__.py
pysd/translators/structures/__init__.py
pysd/translators/structures/abstract_expressions.py
pysd/translators/structures/abstract_model.py
pysd/translators/vensim/__init__.py
pysd/translators/vensim/vensim_element.py
pysd/translators/vensim/vensim_file.py
pysd/translators/vensim/vensim_section.py
pysd/translators/vensim/vensim_structures.py
pysd/translators/vensim/vensim_utils.py
pysd/translators/vensim/parsing_grammars/common_grammar.peg
pysd/translators/vensim/parsing_grammars/components.peg
pysd/translators/vensim/parsing_grammars/element_object.peg
pysd/translators/vensim/parsing_grammars/file_sections.peg
pysd/translators/vensim/parsing_grammars/lookups.peg
pysd/translators/vensim/parsing_grammars/section_elements.peg
pysd/translators/vensim/parsing_grammars/sketch.peg
pysd/translators/xmile/__init__.py
pysd/translators/xmile/xmile_element.py
pysd/translators/xmile/xmile_file.py
pysd/translators/xmile/xmile_section.py
pysd/translators/xmile/xmile_structures.py
pysd/translators/xmile/xmile_utils.py
pysd/translators/xmile/parsing_grammars/equations.peg
pysd-3.14.3.dist-info/LICENSE
pysd-3.14.3.dist-info/METADATA
pysd-3.14.3.dist-info/WHEEL
pysd-3.14.3.dist-info/top_level.txt
pysd-3.14.3.dist-info/RECORD
