Metadata-Version: 2.1
Name: pysd
Version: 3.14.3
Summary: System Dynamics Modeling in Python
Home-page: https://github.com/SDXorg/pysd
Author: PySD contributors
License: LICENSE
Keywords: System Dynamics,Vensim,XMILE
Platform: UNKNOWN
Classifier: Development Status :: 4 - Beta
Classifier: License :: OSI Approved :: MIT License
Classifier: Topic :: Scientific/Engineering :: Mathematics
Classifier: Topic :: Scientific/Engineering :: Information Analysis
Classifier: Intended Audience :: Science/Research
Classifier: Programming Language :: Python :: 3.9
Classifier: Programming Language :: Python :: 3.10
Classifier: Programming Language :: Python :: 3.11
Classifier: Programming Language :: Python :: 3.12
Requires-Python: >=3.9
License-File: LICENSE
